earthquake_alert/__init__.py
IndonesiaLatestEarthQuakeAlert-0.0.8.dist-info/LICENSE
IndonesiaLatestEarthQuakeAlert-0.0.8.dist-info/METADATA
IndonesiaLatestEarthQuakeAlert-0.0.8.dist-info/WHEEL
IndonesiaLatestEarthQuakeAlert-0.0.8.dist-info/top_level.txt
IndonesiaLatestEarthQuakeAlert-0.0.8.dist-info/RECORD
