Metadata-Version: 2.1
Name: IndonesiaLatestEarthQuakeAlert
Version: 0.0.8
Summary: This package will guide us get earth quake information from bmkg
Home-page: https://github.com/fajari/Indonesia-Eartquake-Alert
Author: M Soleh Fajari
Author-email: <m.soleh.fajari@gmail.com>
Classifier: Development Status :: 5 - Production/Stable
Classifier: Programming Language :: Python :: 3
Classifier: License :: OSI Approved :: GNU General Public License v3 (GPLv3)
Classifier: Operating System :: Microsoft :: Windows
Requires-Python: >=3.6
License-File: LICENSE
